pytest_repo_health/__init__.py
pytest_repo_health/plugin.py
pytest_repo_health/utils.py
pytest_repo_health/fixtures/__init__.py
pytest_repo_health/fixtures/git.py
pytest_repo_health/fixtures/github.py
pytest_repo_health-3.2.0.dist-info/licenses/LICENSE
pytest_repo_health-3.2.0.dist-info/METADATA
pytest_repo_health-3.2.0.dist-info/WHEEL
pytest_repo_health-3.2.0.dist-info/entry_points.txt
pytest_repo_health-3.2.0.dist-info/top_level.txt
pytest_repo_health-3.2.0.dist-info/RECORD
