Metadata-Version: 2.4
Name: pytest-repo-health
Version: 3.2.0
Summary: A pytest plugin to report on repository standards conformance
Home-page: https://github.com/edX/pytest-repo-health
Author: edX
Author-email: oscm@edx.org
License: Apache Software License 2.0
Keywords: pytest edx
Classifier: Development Status :: 3 - Alpha
Classifier: Intended Audience :: Developers
Classifier: License :: OSI Approved :: GNU Affero General Public License v3
Classifier: Natural Language :: English
Classifier: Topic :: Software Development :: Testing
Classifier: Programming Language :: Python
Classifier: Programming Language :: Python :: 3
Classifier: Programming Language :: Python :: 3.11
Classifier: Programming Language :: Python :: 3.12
Requires-Python: >=3.11
License-File: LICENSE
Requires-Dist: GitPython
Requires-Dist: pytest
Requires-Dist: pytest-aiohttp
Requires-Dist: pyyaml
Dynamic: author
Dynamic: author-email
Dynamic: classifier
Dynamic: description
Dynamic: description-content-type
Dynamic: home-page
Dynamic: keywords
Dynamic: license
Dynamic: license-file
Dynamic: requires-dist
Dynamic: requires-python
Dynamic: summary
